pjob_cli/__init__.py
pjob_cli/core.py
pjob_cli-0.4.1.dist-info/METADATA
pjob_cli-0.4.1.dist-info/WHEEL
pjob_cli-0.4.1.dist-info/top_level.txt
pjob_cli-0.4.1.dist-info/RECORD
